{
  "annotations": {
    "list": [
      {
        "builtIn": 1,
        "datasource": "-- Grafana --",
        "enable": true,
        "hide": true,
        "iconColor": "rgba(0, 211, 255, 1)",
        "name": "Annotations & Alerts",
        "type": "dashboard"
      }
    ]
  },
  "editable": true,
  "gnetId": null,
  "graphTooltip": 1,
  "id": null,
  "links": [],
  "panels": [
    {
      "datasource": "Prometheus",
      "fieldConfig": {
        "defaults": {
          "color": {
            "mode": "palette-classic"
          },
          "custom": {
            "axisLabel": "",
            "axisPlacement": "auto",
            "barAlignment": 0,
            "drawStyle": "line",
            "fillOpacity": 10,
            "gradientMode": "none",
            "hideFrom": {
              "legend": false,
              "tooltip": false,
              "viz": false
            },
            "lineInterpolation": "linear",
            "lineWidth": 1,
            "pointSize": 5,
            "scaleDistribution": {
              "type": "linear"
            },
            "showPoints": "never",
            "spanNulls": true
          },
          "mappings": [],
          "thresholds": {
            "mode": "absolute",
            "steps": [
              {
                "color": "green",
                "value": null
              },
              {
                "color": "red",
                "value": 80
              }
            ]
          },
          "unit": "reqps"
        },
        "overrides": []
      },
      "gridPos": {
        "h": 8,
        "w": 12,
        "x": 0,
        "y": 0
      },
      "id": 2,
      "options": {
        "legend": {
          "calcs": ["mean", "lastNotNull"],
          "displayMode": "table",
          "placement": "bottom"
        },
        "tooltip": {
          "mode": "single"
        }
      },
      "pluginVersion": "8.0.0",
      "targets": [
        {
          "expr": "sum(rate(http_requests_total[5m])) by (job)",
          "legendFormat": "{{ job }}",
          "refId": "A"
        }
      ],
      "title": "Request Rate by Service",
      "type": "timeseries"
    },
    {
      "datasource": "Prometheus",
      "fieldConfig": {
        "defaults": {
          "color": {
            "mode": "thresholds"
          },
          "mappings": [],
          "thresholds": {
            "mode": "absolute",
            "steps": [
              {
                "color": "green",
                "value": null
              },
              {
                "color": "yellow",
                "value": 50
              },
              {
                "color": "red",
                "value": 100
              }
            ]
          },
          "unit": "currencyUSD"
        },
        "overrides": []
      },
      "gridPos": {
        "h": 8,
        "w": 12,
        "x": 12,
        "y": 0
      },
      "id": 3,
      "options": {
        "orientation": "auto",
        "reduceOptions": {
          "calcs": ["lastNotNull"],
          "fields": "",
          "values": false
        },
        "showThresholdLabels": false,
        "showThresholdMarkers": true,
        "text": {}
      },
      "pluginVersion": "8.0.0",
      "targets": [
        {
          "expr": "sum(rate(ai_token_cost_total[1h])) * 60",
          "legendFormat": "Cost per Hour",
          "refId": "A"
        }
      ],
      "title": "AI Cost per Hour",
      "type": "gauge"
    },
    {
      "datasource": "Prometheus",
      "fieldConfig": {
        "defaults": {
          "color": {
            "mode": "palette-classic"
          },
          "custom": {
            "hideFrom": {
              "legend": false,
              "tooltip": false,
              "viz": false
            }
          },
          "mappings": [],
          "unit": "short"
        },
        "overrides": []
      },
      "gridPos": {
        "h": 8,
        "w": 12,
        "x": 0,
        "y": 8
      },
      "id": 4,
      "options": {
        "legend": {
          "displayMode": "table",
          "placement": "right",
          "values": ["value", "percent"]
        },
        "pieType": "donut",
        "tooltip": {
          "mode": "single"
        }
      },
      "pluginVersion": "8.0.0",
      "targets": [
        {
          "expr": "sum(rate(ai_tokens_used[5m])) by (model)",
          "legendFormat": "{{ model }}",
          "refId": "A"
        }
      ],
      "title": "AI Token Usage by Model",
      "type": "piechart"
    },
    {
      "datasource": "Prometheus",
      "fieldConfig": {
        "defaults": {
          "color": {
            "mode": "thresholds"
          },
          "mappings": [],
          "max": 100,
          "min": 0,
          "thresholds": {
            "mode": "absolute",
            "steps": [
              {
                "color": "red",
                "value": null
              },
              {
                "color": "yellow",
                "value": 1
              },
              {
                "color": "green",
                "value": 5
              }
            ]
          },
          "unit": "percent"
        },
        "overrides": []
      },
      "gridPos": {
        "h": 8,
        "w": 12,
        "x": 12,
        "y": 8
      },
      "id": 5,
      "options": {
        "orientation": "auto",
        "reduceOptions": {
          "calcs": ["mean"],
          "fields": "",
          "values": false
        },
        "showThresholdLabels": false,
        "showThresholdMarkers": true,
        "text": {}
      },
      "pluginVersion": "8.0.0",
      "targets": [
        {
          "expr": "(1 - rate(http_requests_total{status=~\"5..\"}[5m]) / rate(http_requests_total[5m])) * 100",
          "legendFormat": "Success Rate",
          "refId": "A"
        }
      ],
      "title": "Success Rate (5m)",
      "type": "gauge"
    },
    {
      "collapsed": false,
      "datasource": null,
      "gridPos": {
        "h": 1,
        "w": 24,
        "x": 0,
        "y": 16
      },
      "id": 10,
      "panels": [],
      "title": "Service Health",
      "type": "row"
    },
    {
      "datasource": "Prometheus",
      "fieldConfig": {
        "defaults": {
          "color": {
            "mode": "thresholds"
          },
          "custom": {
            "align": "center",
            "displayMode": "color-background",
            "filterable": false
          },
          "mappings": [
            {
              "options": {
                "0": {
                  "color": "red",
                  "index": 0,
                  "text": "DOWN"
                },
                "1": {
                  "color": "green",
                  "index": 1,
                  "text": "UP"
                }
              },
              "type": "value"
            }
          ],
          "thresholds": {
            "mode": "absolute",
            "steps": [
              {
                "color": "red",
                "value": null
              },
              {
                "color": "green",
                "value": 1
              }
            ]
          }
        },
        "overrides": []
      },
      "gridPos": {
        "h": 8,
        "w": 24,
        "x": 0,
        "y": 17
      },
      "id": 6,
      "options": {
        "showHeader": true
      },
      "pluginVersion": "8.0.0",
      "targets": [
        {
          "expr": "up{job=~\"prompt-library|ai-platform|postgres-main|postgres-langfuse|redis|minio|nginx\"}",
          "format": "table",
          "instant": true,
          "refId": "A"
        }
      ],
      "title": "Service Status",
      "transformations": [
        {
          "id": "organize",
          "options": {
            "excludeByName": {
              "Time": true,
              "__name__": true
            },
            "indexByName": {},
            "renameByName": {
              "Value": "Status",
              "instance": "Instance",
              "job": "Service"
            }
          }
        }
      ],
      "type": "table"
    },
    {
      "collapsed": false,
      "datasource": null,
      "gridPos": {
        "h": 1,
        "w": 24,
        "x": 0,
        "y": 25
      },
      "id": 11,
      "panels": [],
      "title": "Performance Metrics",
      "type": "row"
    },
    {
      "datasource": "Prometheus",
      "fieldConfig": {
        "defaults": {
          "color": {
            "mode": "palette-classic"
          },
          "custom": {
            "axisLabel": "",
            "axisPlacement": "auto",
            "barAlignment": 0,
            "drawStyle": "line",
            "fillOpacity": 10,
            "gradientMode": "none",
            "hideFrom": {
              "legend": false,
              "tooltip": false,
              "viz": false
            },
            "lineInterpolation": "linear",
            "lineWidth": 1,
            "pointSize": 5,
            "scaleDistribution": {
              "type": "linear"
            },
            "showPoints": "never",
            "spanNulls": true
          },
          "mappings": [],
          "thresholds": {
            "mode": "absolute",
            "steps": [
              {
                "color": "green",
                "value": null
              },
              {
                "color": "yellow",
                "value": 1
              },
              {
                "color": "red",
                "value": 2
              }
            ]
          },
          "unit": "s"
        },
        "overrides": []
      },
      "gridPos": {
        "h": 8,
        "w": 12,
        "x": 0,
        "y": 26
      },
      "id": 7,
      "options": {
        "legend": {
          "calcs": ["mean", "max"],
          "displayMode": "table",
          "placement": "bottom"
        },
        "tooltip": {
          "mode": "single"
        }
      },
      "pluginVersion": "8.0.0",
      "targets": [
        {
          "expr": "histogram_quantile(0.95, sum(rate(http_request_duration_seconds_bucket[5m])) by (job, le))",
          "legendFormat": "{{ job }} - p95",
          "refId": "A"
        },
        {
          "expr": "histogram_quantile(0.99, sum(rate(http_request_duration_seconds_bucket[5m])) by (job, le))",
          "legendFormat": "{{ job }} - p99",
          "refId": "B"
        }
      ],
      "title": "Response Time Percentiles",
      "type": "timeseries"
    },
    {
      "datasource": "Prometheus",
      "fieldConfig": {
        "defaults": {
          "color": {
            "mode": "palette-classic"
          },
          "custom": {
            "axisLabel": "",
            "axisPlacement": "auto",
            "barAlignment": 0,
            "drawStyle": "line",
            "fillOpacity": 10,
            "gradientMode": "none",
            "hideFrom": {
              "legend": false,
              "tooltip": false,
              "viz": false
            },
            "lineInterpolation": "linear",
            "lineWidth": 1,
            "pointSize": 5,
            "scaleDistribution": {
              "type": "linear"
            },
            "showPoints": "never",
            "spanNulls": true
          },
          "mappings": [],
          "thresholds": {
            "mode": "absolute",
            "steps": [
              {
                "color": "green",
                "value": null
              }
            ]
          },
          "unit": "short"
        },
        "overrides": []
      },
      "gridPos": {
        "h": 8,
        "w": 12,
        "x": 12,
        "y": 26
      },
      "id": 8,
      "options": {
        "legend": {
          "calcs": [],
          "displayMode": "list",
          "placement": "bottom"
        },
        "tooltip": {
          "mode": "single"
        }
      },
      "pluginVersion": "8.0.0",
      "targets": [
        {
          "expr": "active_traces_count",
          "legendFormat": "Active Traces",
          "refId": "A"
        }
      ],
      "title": "Active AI Traces",
      "type": "timeseries"
    },
    {
      "collapsed": false,
      "datasource": null,
      "gridPos": {
        "h": 1,
        "w": 24,
        "x": 0,
        "y": 34
      },
      "id": 12,
      "panels": [],
      "title": "Resource Usage",
      "type": "row"
    },
    {
      "datasource": "Prometheus",
      "fieldConfig": {
        "defaults": {
          "color": {
            "mode": "palette-classic"
          },
          "custom": {
            "axisLabel": "",
            "axisPlacement": "auto",
            "barAlignment": 0,
            "drawStyle": "line",
            "fillOpacity": 10,
            "gradientMode": "none",
            "hideFrom": {
              "legend": false,
              "tooltip": false,
              "viz": false
            },
            "lineInterpolation": "linear",
            "lineWidth": 1,
            "pointSize": 5,
            "scaleDistribution": {
              "type": "linear"
            },
            "showPoints": "never",
            "spanNulls": true
          },
          "mappings": [],
          "max": 100,
          "min": 0,
          "thresholds": {
            "mode": "absolute",
            "steps": [
              {
                "color": "green",
                "value": null
              },
              {
                "color": "yellow",
                "value": 80
              },
              {
                "color": "red",
                "value": 90
              }
            ]
          },
          "unit": "percent"
        },
        "overrides": []
      },
      "gridPos": {
        "h": 8,
        "w": 12,
        "x": 0,
        "y": 35
      },
      "id": 9,
      "options": {
        "legend": {
          "calcs": [],
          "displayMode": "list",
          "placement": "bottom"
        },
        "tooltip": {
          "mode": "single"
        }
      },
      "pluginVersion": "8.0.0",
      "targets": [
        {
          "expr": "(container_memory_usage_bytes / container_spec_memory_limit_bytes) * 100",
          "legendFormat": "{{ container_name }}",
          "refId": "A"
        }
      ],
      "title": "Container Memory Usage %",
      "type": "timeseries"
    }
  ],
  "refresh": "10s",
  "schemaVersion": 27,
  "style": "dark",
  "tags": ["ai-platform", "overview"],
  "templating": {
    "list": []
  },
  "time": {
    "from": "now-1h",
    "to": "now"
  },
  "timepicker": {},
  "timezone": "",
  "title": "SambaTV AI Platform Overview",
  "uid": "ai-platform-overview",
  "version": 0
}